README.md
setup.py
wanplusapi/__init__.py
wanplusapi/call_api.py
wanplusapi/wanplusapi.py
wanplusapi.egg-info/PKG-INFO
wanplusapi.egg-info/SOURCES.txt
wanplusapi.egg-info/dependency_links.txt
wanplusapi.egg-info/requires.txt
wanplusapi.egg-info/top_level.txt